<?xml version="1.0" encoding="utf-8"?>
<!DOCTYPE hibernate-mapping PUBLIC "-//Hibernate/Hibernate Mapping DTD 3.0//EN"
"http://hibernate.sourceforge.net/hibernate-mapping-3.0.dtd">
<!-- 
    Mapping file autogenerated by MyEclipse Persistence Tools
-->
<hibernate-mapping>
    <class name="com.entity.basedata.DepartTec" table="DepartTec" schema="dbo" catalog="bysj">
        <id name="dtid" type="java.lang.Integer">
            <column name="DTid" />
            <generator class="identity" />
        </id>
        <property name="departid" type="java.lang.Integer">
            <column name="Departid" />
        </property>
        <property name="teccode" type="java.lang.String">
            <column name="Teccode" length="50" />
        </property>
        <property name="tecrole" type="java.lang.Integer">
            <column name="Tecrole" />
        </property>
    </class>
</hibernate-mapping>
